README.md
setup.cfg
setup.py
sklearn_utils/__init__.py
sklearn_utils/tests.py
sklearn_utils.egg-info/PKG-INFO
sklearn_utils.egg-info/SOURCES.txt
sklearn_utils.egg-info/dependency_links.txt
sklearn_utils.egg-info/requires.txt
sklearn_utils.egg-info/top_level.txt
sklearn_utils/noise/__init__.py
sklearn_utils/noise/noise_preprocessing.py
sklearn_utils/noise/select_not_k_best.py
sklearn_utils/noise/tests.py
sklearn_utils/preprocessing/__init__.py
sklearn_utils/preprocessing/dynamic_pipeline.py
sklearn_utils/preprocessing/feature_merger.py
sklearn_utils/preprocessing/feature_renaming.py
sklearn_utils/preprocessing/fold_change_preprocessing.py
sklearn_utils/preprocessing/functional_enrichment_analysis.py
sklearn_utils/preprocessing/inverse_dict_vectorizer.py
sklearn_utils/preprocessing/standard_scale_by_label.py
sklearn_utils/preprocessing/tests.py
sklearn_utils/utils/__init__.py
sklearn_utils/utils/data_utils.py
sklearn_utils/utils/skutils_io.py
sklearn_utils/utils/tests.py
sklearn_utils/visualization/__init__.py
sklearn_utils/visualization/heatmap.py
sklearn_utils/visualization/tests.py