Metadata-Version: 1.1
Name: sklearn-utils
Version: 0.0.14
Summary: Sklearn utils
Home-page: https://github.com/MuhammedHasan/sklearn_utils
Author: Muhammed Hasan Celik
Author-email: hasancelik@std.sehir.edu.tr
License: UNKNOWN
Keywords: scikit-learn,machine-learning,utility-library
Platform: UNKNOWN
Classifier: Programming Language :: Python :: 3.4
Classifier: Programming Language :: Python :: 3.5
Classifier: Programming Language :: Python :: 3.6
